{"layout_key":"zoom_grid_4","ver":1,"windows":{"1":{"left":0,"top":0,"right":0.6968,"bottom":1,"z_order":0,"radius":0,"config_id":"layout_linkmic_panel_4_main","business_id":"linkmic_grid_enlarge_4_max"},"2":{"left":0.7021,"top":0,"right":1,"bottom":0.3294,"z_order":0,"radius":0,"config_id":"layout_linkmic_grid_9","business_id":"linkmic_grid_enlarge_4_min"},"3":{"left":0.7021,"top":0.3353,"right":1,"bottom":0.6647,"z_order":0,"radius":0,"config_id":"layout_linkmic_grid_9","business_id":"linkmic_grid_enlarge_4_min"},"4":{"left":0.7021,"top":0.6706,"right":1,"bottom":1,"z_order":0,"radius":0,"config_id":"layout_linkmic_grid_9","business_id":"linkmic_grid_enlarge_4_min"}},"ratio":1.1,"link_layout_container":{"mode":"central_operat","has_split_line":true}}